STRIDE/MFPT.py
STRIDE/__init__.py
STRIDE/main.py
hicstride-1.0.1.dist-info/licenses/LICENSE
hicstride-1.0.1.dist-info/METADATA
hicstride-1.0.1.dist-info/WHEEL
hicstride-1.0.1.dist-info/entry_points.txt
hicstride-1.0.1.dist-info/top_level.txt
hicstride-1.0.1.dist-info/RECORD
