Metadata-Version: 2.4
Name: hicstride
Version: 1.0.1
Summary: STRIDE: A Robust Dissimilarity Measurement for Chromatin Conformation Capture Data Based on Sequencing Depth-Insensitive Representation.
Home-page: https://gitee.com/matrix_evolution/STRIDE
Author: Bingxiang Xu
Author-email: xubingxiang@sus.edu.cn
Requires-Python: >=3.11
License-File: LICENSE
Requires-Dist: numpy>=1.23.4
Requires-Dist: scipy>=1.12.0
Requires-Dist: pandas>=2.2.1
Requires-Dist: joblib>=1.3.2
Requires-Dist: h5py>=3.10.0
Dynamic: author
Dynamic: author-email
Dynamic: description
Dynamic: description-content-type
Dynamic: home-page
Dynamic: license-file
Dynamic: requires-dist
Dynamic: requires-python
Dynamic: summary
